signing/__init__.py
signing/signing.py
astaria_signing_lib-0.1.dist-info/METADATA
astaria_signing_lib-0.1.dist-info/WHEEL
astaria_signing_lib-0.1.dist-info/top_level.txt
astaria_signing_lib-0.1.dist-info/RECORD
