Metadata-Version: 2.1
Name: astaria-signing-lib
Version: 0.1
Requires-Dist: web3
